[
  {
    "product_id": "P001",
    "name": "Wireless Bluetooth Headphones",
    "category": "Electronics", "category_id":1,
    "price": 59.99,
    "description": "High-quality wireless Bluetooth headphones with noise cancellation.",
    "in_stock": true,
    "rating": 4.5,
    "reviews": 120,
    "discount": 10
  },
  {
    "product_id": "P002",
    "name": "Stainless Steel Water Bottle",
    "category": "Home & Kitchen", "category_id":2,
    "price": 19.99,
    "description": "Durable stainless steel water bottle with a leak-proof cap.",
    "in_stock": true,
    "rating": 4.8,
    "reviews": 200,
    "discount": 5
  },
  {
    "product_id": "P003",
    "name": "Yoga Mat",
    "category": "Sports & Outdoors", "category_id":3,
    "price": 29.99,
    "description": "Non-slip yoga mat with extra cushioning for comfort.",
    "in_stock": false,
    "rating": 4.2,
    "reviews": 95,
    "discount": 15
  },
  {
    "product_id": "P004",
    "name": "LED Desk Lamp",
    "category": "Office Supplies", "category_id":4,
    "price": 39.99,
    "description": "Adjustable LED desk lamp with touch control and USB charging port.",
    "in_stock": true,
    "rating": 4.7,
    "reviews": 150,
    "discount": 20
  },
  {
    "product_id": "P005",
    "name": "Electric Kettle",
    "category": "Home & Kitchen", "category_id":2,
    "price": 24.99,
    "description": "1.7-liter electric kettle with auto shut-off and boil-dry protection.",
    "in_stock": false,
    "rating": 4.1,
    "reviews": 80,
    "discount": 10
  },
  {
    "product_id": "P006",
    "name": "Gaming Mouse",
    "category": "Electronics", "category_id":1,
    "price": 49.99,
    "description": "Ergonomic gaming mouse with customizable buttons and RGB lighting.",
    "in_stock": true,
    "rating": 4.6,
    "reviews": 110,
    "discount": 5
  },
  {
    "product_id": "P007",
    "name": "Cookware Set",
    "category": "Home & Kitchen", "category_id":2,
    "price": 89.99,
    "description": "10-piece non-stick cookware set including pots, pans, and utensils.",
    "in_stock": true,
    "rating": 4.3,
    "reviews": 60,
    "discount": 25
  },
  {
    "product_id": "P008",
    "name": "Running Shoes",
    "category": "Sports & Outdoors", "category_id":3,
    "price": 79.99,
    "description": "Lightweight running shoes with breathable mesh and cushioned sole.",
    "in_stock": true,
    "rating": 4.4,
    "reviews": 140,
    "discount": 10
  },
  {
    "product_id": "P009",
    "name": "Smart Watch",
    "category": "Electronics", "category_id":1,
    "price": 199.99,
    "description": "Water-resistant smart watch with fitness tracking and notifications.",
    "in_stock": false,
    "rating": 4.5,
    "reviews": 85,
    "discount": 15
  },
  {
    "product_id": "P010",
    "name": "Wireless Charger",
    "category": "Electronics", "category_id":1,
    "price": 29.99,
    "description": "Fast wireless charger compatible with all Qi-enabled devices.",
    "in_stock": true,
    "rating": 4.2,
    "reviews": 100,
    "discount": 20
  },
  {
    "product_id": "P011",
    "name": "Electric Toothbrush",
    "category": "Health & Personal Care", "category_id":5,
    "price": 49.99,
    "description": "Rechargeable electric toothbrush with multiple cleaning modes.",
    "in_stock": true,
    "rating": 4.7,
    "reviews": 220,
    "discount": 10
  },
  {
    "product_id": "P012",
    "name": "Portable Power Bank",
    "category": "Electronics", "category_id":1,
    "price": 39.99,
    "description": "10000mAh portable power bank with fast charging capability.",
    "in_stock": true,
    "rating": 4.5,
    "reviews": 180,
    "discount": 15
  },
  {
    "product_id": "P013",
    "name": "Noise Cancelling Earbuds",
    "category": "Electronics", "category_id":1,
    "price": 89.99,
    "description": "Wireless noise-cancelling earbuds with superior sound quality.",
    "in_stock": false,
    "rating": 4.8,
    "reviews": 250,
    "discount": 20
  },
  {
    "product_id": "P014",
    "name": "Smartphone Stand",
    "category": "Accessories", "category_id":6,
    "price": 14.99,
    "description": "Adjustable smartphone stand compatible with all phone models.",
    "in_stock": true,
    "rating": 4.3,
    "reviews": 60,
    "discount": 5
  },
  {
    "product_id": "P015",
    "name": "Fitness Tracker",
    "category": "Electronics", "category_id":1,
    "price": 59.99,
    "description": "Fitness tracker with heart rate monitor and step counter.",
    "in_stock": true,
    "rating": 4.6,
    "reviews": 130,
    "discount": 10
  },
  {
    "product_id": "P016",
    "name": "Travel Backpack",
    "category": "Luggage & Travel", "category_id":7,
    "price": 79.99,
    "description": "Water-resistant travel backpack with multiple compartments.",
    "in_stock": false,
    "rating": 4.4,
    "reviews": 95,
    "discount": 25
  },
  {
    "product_id": "P017",
    "name": "Desk Organizer",
    "category": "Office Supplies", "category_id":4,
    "price": 24.99,
    "description": "Multi-functional desk organizer with drawers and compartments.",
    "in_stock": true,
    "rating": 4.1,
    "reviews": 75,
    "discount": 10
  },
  {
    "product_id": "P018",
    "name": "Instant Pot",
    "category": "Home & Kitchen", "category_id":2,
    "price": 99.99,
    "description": "7-in-1 electric pressure cooker with programmable settings.",
    "in_stock": true,
    "rating": 4.7,
    "reviews": 300,
    "discount": 15
  },
  {
    "product_id": "P019",
    "name": "Cordless Vacuum Cleaner",
    "category": "Home & Kitchen", "category_id":2,
    "price": 149.99,
    "description": "Lightweight cordless vacuum cleaner with powerful suction.",
    "in_stock": false,
    "rating": 4.5,
    "reviews": 210,
    "discount": 20
  },
  {
    "product_id": "P020",
    "name": "4K UHD Monitor",
    "category": "Electronics", "category_id":1,
    "price": 299.99,
    "description": "27-inch 4K UHD monitor with HDR and slim bezel design.",
    "in_stock": true,
    "rating": 4.8,
    "reviews": 160,
    "discount": 25
  },
  {
    "product_id": "P021",
    "name": "Smart Thermostat",
    "category": "Home Automation", "category_id":8,
    "price": 129.99,
    "description": "Wi-Fi enabled smart thermostat with voice control compatibility.",
    "in_stock": true,
    "rating": 4.6,
    "reviews": 140,
    "discount": 15
  },
  {
    "product_id": "P022",
    "name": "Electric Standing Desk",
    "category": "Office Furniture", "category_id":9,
    "price": 399.99,
    "description": "Height-adjustable electric standing desk with memory presets.",
    "in_stock": false,
    "rating": 4.7,
    "reviews": 85,
    "discount": 20
  },
  {
    "product_id": "P023",
    "name": "Air Fryer",
    "category": "Home & Kitchen", "category_id":2,
    "price": 89.99,
    "description": "5.8-quart air fryer with digital touchscreen and presets.",
    "in_stock": true,
    "rating": 4.5,
    "reviews": 180,
    "discount": 10
  },
  {
    "product_id": "P024",
    "name": "Gaming Chair",
    "category": "Furniture", "category_id":10,
    "price": 159.99,
    "description": "Ergonomic gaming chair with lumbar support and recline function.",
    "in_stock": true,
    "rating": 4.4,
    "reviews": 120,
    "discount": 15
  },
  {
    "product_id": "P025",
    "name": "Digital Photo Frame",
    "category": "Electronics", "category_id":1,
    "price": 79.99,
    "description": "10-inch digital photo frame with Wi-Fi and cloud storage.",
    "in_stock": true,
    "rating": 4.2,
    "reviews": 95,
    "discount": 10
  },
  {
    "product_id": "P026",
    "name": "Wireless Earbuds",
    "category": "Electronics", "category_id":1,
    "price": 59.99,
    "description": "Noise-cancelling wireless earbuds with 24-hour battery life.",
    "in_stock": true,
    "rating": 4.5,
    "reviews": 150,
    "discount": 15
  },
  {
    "product_id": "P027",
    "name": "Smartwatch",
    "category": "Electronics", "category_id":1,
    "price": 129.99,
    "description": "Water-resistant smartwatch with heart rate monitor and GPS.",
    "in_stock": true,
    "rating": 4.0,
    "reviews": 200,
    "discount": 20
},
{
    "product_id": "P027",
    "name": "Smartwatch",
    "category": "Electronics", "category_id":1,
    "price": 129.99,
    "description": "Water-resistant smartwatch with heart rate monitor and GPS.",
    "in_stock": true,
    "rating": 4.0,
    "reviews": 200,
    "discount": 20
},
{
    "product_id": "P028",
    "name": "Bluetooth Speaker",
    "category": "Electronics", "category_id":1,
    "price": 39.99,
    "description": "Portable Bluetooth speaker with 10-hour playtime and rich bass.",
    "in_stock": false,
    "rating": 4.3,
    "reviews": 85,
    "discount": 5
},
{
    "product_id": "P029",
    "name": "4K Ultra HD TV",
    "category": "Electronics", "category_id":1,
    "price": 499.99,
    "description": "55-inch 4K Ultra HD TV with HDR and smart functionality.",
    "in_stock": true,
    "rating": 4.7,
    "reviews": 300,
    "discount": 25
},
{
    "product_id": "P030",
    "name": "Laptop",
    "category": "Electronics", "category_id":1,
    "price": 899.99,
    "description": "15.6-inch laptop with Intel i7 processor, 16GB RAM, and 512GB SSD.",
    "in_stock": true,
    "rating": 4.6,
    "reviews": 180,
    "discount": 30
},
{
    "product_id": "P031",
    "name": "Running Shoes",
    "category": "Sportswear", "category_id":11,
    "price": 89.99,
    "description": "Lightweight running shoes with breathable mesh and cushioned sole.",
    "in_stock": true,
    "rating": 4.3,
    "reviews": 110,
    "discount": 10
},{
    "product_id": "P032",
    "name": "Blender",
    "category": "Home Appliances", "category_id":12,
    "price": 49.99,
    "description": "High-speed blender with multiple settings and 1.5-liter jar.",
    "in_stock": true,
    "rating": 4.1,
    "reviews": 75,
    "discount": 5
},
{
    "product_id": "P033",
    "name": "Gaming Chair",
    "category": "Furniture", "category_id":10,
    "price": 149.99,
    "description": "Ergonomic gaming chair with adjustable height and lumbar support.",
    "in_stock": false,
    "rating": 4.4,
    "reviews": 120
},{
    "product_id": "P034",
    "name": "Electric Toothbrush",
    "category": "Health & Personal Care", "category_id":5,
    "price": 39.99,
    "description": "Rechargeable electric toothbrush with 3 brushing modes and timer.",
    "in_stock": true,
    "rating": 4.6,
    "reviews": 220,
    "discount": 10
},
{
    "product_id": "P035",
    "name": "Yoga Mat",
    "category": "Fitness", "category_id":13,
    "price": 29.99,
    "description": "Non-slip yoga mat with carrying strap and 6mm thickness.",
    "in_stock": true,
    "rating": 4.7,
    "reviews": 90,
    "discount": 5
},
{
    "product_id": "P036",
    "name": "Coffee Maker",
    "category": "Kitchen Appliances", "category_id":14,
    "price": 89.99,
    "description": "12-cup programmable coffee maker with auto shut-off and brew strength control.",
    "in_stock": true,
    "rating": 4.5,
    "reviews": 140,
    "discount": 15
},{
    "product_id": "P037",
    "name": "Smart Thermostat",
    "category": "Home Improvement", "category_id":15,
    "price": 199.99,
    "description": "Wi-Fi enabled smart thermostat with energy-saving features and remote control.",
    "in_stock": true,
    "rating": 4.8,
    "reviews": 180,
    "discount": 20
},{
    "product_id": "P038",
    "name": "Noise-Cancelling Headphones",
    "category": "Electronics", "category_id":1,
    "price": 129.99,
    "description": "Over-ear noise-cancelling headphones with Bluetooth and 30-hour battery life.",
    "in_stock": true,
    "rating": 4.6,
    "reviews": 250,
    "discount": 20
},{
    "product_id": "P039",
    "name": "LED Desk Lamp",
    "category": "Office Supplies", "category_id":4,
    "price": 24.99,
    "description": "Adjustable LED desk lamp with touch control and USB charging port.",
    "in_stock": true,
    "rating": 4.5,
    "reviews": 60,
    "discount": 10
},{
    "product_id": "P040",
    "name": "Robot Vacuum Cleaner",
    "category": "Home Appliances", "category_id":12,
    "price": 299.99,
    "description": "Wi-Fi connected robot vacuum cleaner with smart mapping and self-charging.",
    "in_stock": true,
    "rating": 4.4,
    "reviews": 310,
    "discount": 25
},{
    "product_id": "P041",
    "name": "Mountain Bike",
    "category": "Sports Equipment", "category_id":16,
    "price": 599.99,
    "description": "21-speed mountain bike with aluminum frame and front suspension.",
    "in_stock": true,
    "rating": 4.3,
    "reviews": 45,
    "discount": 20
},
{
    "product_id": "P042",
    "name": "Electric Kettle",
    "category": "Kitchen Appliances", "category_id":14,
    "price": 49.99,
    "description": "1.7-liter electric kettle with stainless steel body and auto shut-off.",
    "in_stock": true,
    "rating": 4.7,
    "reviews": 85,
    "discount": 10
},{
    "product_id": "P043",
    "name": "Digital Camera",
    "category": "Photography", "category_id":17,
    "price": 399.99,
    "description": "Compact digital camera with 20.1 MP sensor, 4K video recording, and Wi-Fi.",
    "in_stock": true,
    "rating": 4.5,
    "reviews": 130,
    "discount": 15
},{
    "product_id": "P044",
    "name": "Portable Power Bank",
    "category": "Electronics", "category_id":1,
    "price": 29.99,
    "description": "10000mAh portable power bank with dual USB ports and fast charging.",
    "in_stock": false,
    "rating": 4.2,
    "reviews": 75,
    "discount": 5
},{
    "product_id": "P045",
    "name": "Electric Guitar",
    "category": "Musical Instruments", "category_id":18,
    "price": 299.99,
    "description": "Solid body electric guitar with 22 frets, 3 pickups, and maple neck.",
    "in_stock": true,
    "rating": 4.6,
    "reviews": 50,
    "discount": 20
},
{
    "product_id": "P046",
    "name": "Camping Tent",
    "category": "Outdoor Gear", "category_id":19,
    "price": 149.99,
    "description": "4-person waterproof camping tent with easy setup and durable material.",
    "in_stock": true,
    "rating": 4.3,
    "reviews": 95,
    "discount": 15
},{
    "product_id": "P047",
    "name": "Smart Light Bulb",
    "category": "Home Improvement", "category_id":15,
    "price": 19.99,
    "description": "Wi-Fi enabled smart light bulb with color changing and voice control.",
    "in_stock": false,
    "rating": 4.5,
    "reviews": 100,
    "discount": 10
},{
    "product_id": "P048",
    "name": "Air Fryer",
    "category": "Kitchen Appliances", "category_id":14,
    "price": 79.99,
    "description": "5.8-quart air fryer with digital touchscreen and multiple cooking presets.",
    "in_stock": true,
    "rating": 4.7,
    "reviews": 160,
    "discount": 20
},
{
    "product_id": "P049",
    "name": "Smartwatch",
    "category": "Wearable Technology", "category_id":20,
    "price": 199.99,
    "description": "Water-resistant smartwatch with fitness tracking and notifications.",
    "in_stock": true,
    "rating": 4.4,
    "reviews": 180,
    "discount": 15
},{
    "product_id": "P050",
    "name": "Electric Scooter",
    "category": "Outdoor Recreation", "category_id":21,
    "price": 499.99,
    "description": "Foldable electric scooter with 15-mile range and 18 mph top speed.",
    "in_stock": false,
    "rating": 4.3,
    "reviews": 70,
    "discount": 25
}

]
